django_stack_inspector/__init__.py
django_stack_inspector-1.0.0.dist-info/METADATA
django_stack_inspector-1.0.0.dist-info/WHEEL
django_stack_inspector-1.0.0.dist-info/LICENSE
django_stack_inspector-1.0.0.dist-info/RECORD
