Metadata-Version: 2.1
Name: django-stack-inspector
Version: 1.0.0
Summary: Inspect the current Python call stack to determine if the Django app is just starting up or already running.
Home-page: https://github.com/Beep-Boop-Digital/django-stack-inspector
Author: Adam McKay
Author-email: adam@beepboop.digital
Requires-Python: >=3.9,<4.0
Classifier: Programming Language :: Python :: 3
Classifier: Programming Language :: Python :: 3.9
Classifier: Programming Language :: Python :: 3.10
Classifier: Programming Language :: Python :: 3.11
Requires-Dist: Django (>3.2)
Project-URL: Repository, https://github.com/Beep-Boop-Digital/django-stack-inspector
